statmaniac/__init__.py
statmaniac/statisticsmaniac.py
statisticsmaniac-0.0.3.dist-info/LICENSE.txt
statisticsmaniac-0.0.3.dist-info/METADATA
statisticsmaniac-0.0.3.dist-info/WHEEL
statisticsmaniac-0.0.3.dist-info/top_level.txt
statisticsmaniac-0.0.3.dist-info/RECORD
